sxpyr/__init__.py
sxpyr/_exports.py
sxpyr/char.py
sxpyr/cli.py
sxpyr/introspect.py
sxpyr/sxpyr.py
sxpyr/walks.py
sxpyr-0.0.4.dist-info/LICENSE
sxpyr-0.0.4.dist-info/METADATA
sxpyr-0.0.4.dist-info/WHEEL
sxpyr-0.0.4.dist-info/top_level.txt
sxpyr-0.0.4.dist-info/RECORD
