Metadata-Version: 2.1
Name: sxpyr
Version: 0.0.4
Summary: A flexible Lisp reader.
Home-page: https://github.com/tgbugs/sxpyr
Author: Tom Gillespie
Author-email: tgbugs@gmail.com
License: MIT
Keywords: lisp reader edn clojure racket scheme elisp emacs sexp s-expression parser parsing
Classifier: Development Status :: 3 - Alpha
Classifier: License :: OSI Approved :: MIT License
Classifier: Programming Language :: Python :: 3.6
Classifier: Programming Language :: Python :: 3.7
Classifier: Programming Language :: Python :: 3.8
Classifier: Programming Language :: Python :: 3.9
Classifier: Programming Language :: Python :: 3.10
Classifier: Programming Language :: Python :: 3.11
Classifier: Programming Language :: Python :: Implementation :: CPython
Classifier: Programming Language :: Python :: Implementation :: PyPy
Classifier: Operating System :: POSIX :: Linux
Classifier: Operating System :: MacOS :: MacOS X
Classifier: Operating System :: Microsoft :: Windows
Requires-Python: >=3.6
License-File: LICENSE
Provides-Extra: cli
Requires-Dist: clifn ; extra == 'cli'
Provides-Extra: fuzz
Requires-Dist: python-afl ; extra == 'fuzz'
Requires-Dist: clifn ; extra == 'fuzz'
Provides-Extra: test
Requires-Dist: pytest ; extra == 'test'
Requires-Dist: clifn ; extra == 'test'
